{
  "fallback_recipes": [
    {
      "id": 1,
      "title": "Simple Pasta with Garlic and Olive Oil",
      "ready_in_minutes": 20,
      "servings": 4,
      "source_url": null,
      "image": null,
      "summary": "A classic Italian pasta dish that's simple, delicious, and perfect when external recipe APIs are unavailable.",
      "instructions": "1. Cook pasta according to package directions. 2. Heat olive oil in a large pan. 3. Add minced garlic and cook until fragrant. 4. Toss cooked pasta with garlic oil. 5. Season with salt, pepper, and red pepper flakes. 6. Serve with grated Parmesan cheese.",
      "cuisines": ["Italian"],
      "dish_types": ["main course"],
      "diets": ["vegetarian"],
      "health_score": 75.0,
      "price_per_serving": 2.50,
      "vegetarian": true,
      "vegan": false,
      "gluten_free": false,
      "dairy_free": false,
      "very_healthy": false,
      "cheap": true,
      "very_popular": true,
      "sustainable": true,
      "ingredients": [
        {"name": "pasta", "amount": 1, "unit": "lb"},
        {"name": "olive oil", "amount": 0.25, "unit": "cup"},
        {"name": "garlic", "amount": 4, "unit": "cloves"},
        {"name": "red pepper flakes", "amount": 0.5, "unit": "tsp"},
        {"name": "parmesan cheese", "amount": 0.5, "unit": "cup"}
      ]
    },
    {
      "id": 2,
      "title": "Basic Green Salad",
      "ready_in_minutes": 10,
      "servings": 2,
      "source_url": null,
      "image": null,
      "summary": "A fresh and healthy salad that's perfect as a side dish or light meal.",
      "instructions": "1. Wash and dry mixed greens. 2. Slice cucumber and tomatoes. 3. Combine vegetables in a large bowl. 4. Whisk together olive oil, vinegar, salt, and pepper for dressing. 5. Toss salad with dressing just before serving.",
      "cuisines": ["American", "Mediterranean"],
      "dish_types": ["salad", "side dish"],
      "diets": ["vegetarian", "vegan", "gluten-free"],
      "health_score": 95.0,
      "price_per_serving": 3.00,
      "vegetarian": true,
      "vegan": true,
      "gluten_free": true,
      "dairy_free": true,
      "very_healthy": true,
      "cheap": false,
      "very_popular": true,
      "sustainable": true,
      "ingredients": [
        {"name": "mixed greens", "amount": 4, "unit": "cups"},
        {"name": "cucumber", "amount": 1, "unit": "medium"},
        {"name": "tomatoes", "amount": 2, "unit": "medium"},
        {"name": "olive oil", "amount": 2, "unit": "tbsp"},
        {"name": "balsamic vinegar", "amount": 1, "unit": "tbsp"}
      ]
    },
    {
      "id": 3,
      "title": "Scrambled Eggs",
      "ready_in_minutes": 5,
      "servings": 2,
      "source_url": null,
      "image": null,
      "summary": "Perfect scrambled eggs that are creamy and delicious.",
      "instructions": "1. Crack eggs into a bowl and whisk with salt and pepper. 2. Heat butter in a non-stick pan over medium-low heat. 3. Pour in eggs and let sit for 20 seconds. 4. Gently stir with a spatula, pushing eggs from edges to center. 5. Continue cooking and stirring until eggs are just set. 6. Remove from heat and serve immediately.",
      "cuisines": ["American", "International"],
      "dish_types": ["breakfast", "brunch"],
      "diets": ["vegetarian", "gluten-free"],
      "health_score": 80.0,
      "price_per_serving": 1.50,
      "vegetarian": true,
      "vegan": false,
      "gluten_free": true,
      "dairy_free": false,
      "very_healthy": true,
      "cheap": true,
      "very_popular": true,
      "sustainable": false,
      "ingredients": [
        {"name": "eggs", "amount": 4, "unit": "large"},
        {"name": "butter", "amount": 1, "unit": "tbsp"},
        {"name": "salt", "amount": 0.25, "unit": "tsp"},
        {"name": "black pepper", "amount": 0.125, "unit": "tsp"}
      ]
    },
    {
      "id": 4,
      "title": "Rice and Beans",
      "ready_in_minutes": 25,
      "servings": 4,
      "source_url": null,
      "image": null,
      "summary": "A nutritious and filling combination that's a staple in many cuisines around the world.",
      "instructions": "1. Cook rice according to package directions. 2. Heat oil in a large pan. 3. Sauté onion and garlic until softened. 4. Add beans, cumin, and paprika. 5. Cook for 5 minutes, stirring occasionally. 6. Season with salt and pepper. 7. Serve beans over rice.",
      "cuisines": ["Latin American", "Caribbean"],
      "dish_types": ["main course"],
      "diets": ["vegetarian", "vegan", "gluten-free"],
      "health_score": 85.0,
      "price_per_serving": 2.00,
      "vegetarian": true,
      "vegan": true,
      "gluten_free": true,
      "dairy_free": true,
      "very_healthy": true,
      "cheap": true,
      "very_popular": true,
      "sustainable": true,
      "ingredients": [
        {"name": "rice", "amount": 1, "unit": "cup"},
        {"name": "black beans", "amount": 1, "unit": "can"},
        {"name": "onion", "amount": 1, "unit": "medium"},
        {"name": "garlic", "amount": 2, "unit": "cloves"},
        {"name": "cumin", "amount": 1, "unit": "tsp"},
        {"name": "paprika", "amount": 0.5, "unit": "tsp"}
      ]
    },
    {
      "id": 5,
      "title": "Grilled Chicken Breast",
      "ready_in_minutes": 20,
      "servings": 4,
      "source_url": null,
      "image": null,
      "summary": "Simple grilled chicken breast that's healthy and versatile.",
      "instructions": "1. Preheat grill to medium-high heat. 2. Season chicken breasts with salt, pepper, and herbs. 3. Brush with olive oil. 4. Grill for 6-7 minutes per side until internal temperature reaches 165°F. 5. Let rest for 5 minutes before slicing. 6. Serve with your favorite sides.",
      "cuisines": ["American", "Mediterranean"],
      "dish_types": ["main course"],
      "diets": ["gluten-free", "dairy-free"],
      "health_score": 90.0,
      "price_per_serving": 4.00,
      "vegetarian": false,
      "vegan": false,
      "gluten_free": true,
      "dairy_free": true,
      "very_healthy": true,
      "cheap": false,
      "very_popular": true,
      "sustainable": false,
      "ingredients": [
        {"name": "chicken breast", "amount": 1.5, "unit": "lbs"},
        {"name": "olive oil", "amount": 2, "unit": "tbsp"},
        {"name": "salt", "amount": 1, "unit": "tsp"},
        {"name": "black pepper", "amount": 0.5, "unit": "tsp"},
        {"name": "dried herbs", "amount": 1, "unit": "tsp"}
      ]
    }
  ],
  "metadata": {
    "source": "Local Fallback Recipe Database",
    "date_created": "2025-07-15T12:00:00Z",
    "description": "Basic recipes for fallback scenarios when external APIs are unavailable",
    "total_recipes": 5,
    "cuisine_coverage": ["Italian", "American", "Mediterranean", "Latin American", "Caribbean"],
    "dietary_options": ["vegetarian", "vegan", "gluten-free", "dairy-free"],
    "difficulty_levels": ["easy"],
    "prep_time_range": "5-25 minutes"
  }
}